securicad/azure_collector/__init__.py
securicad/azure_collector/__main__.py
securicad/azure_collector/main.py
securicad/azure_collector/schema_classes.py
securicad/azure_collector/services/ad_groups.py
securicad/azure_collector/services/api_management.py
securicad/azure_collector/services/app_service_plans.py
securicad/azure_collector/services/app_services.py
securicad/azure_collector/services/application_insights.py
securicad/azure_collector/services/container_registries.py
securicad/azure_collector/services/cosmos_databases.py
securicad/azure_collector/services/disks.py
securicad/azure_collector/services/hva_tagging.py
securicad/azure_collector/services/key_vaults.py
securicad/azure_collector/services/kubernetes_clusters.py
securicad/azure_collector/services/local_network_gateways.py
securicad/azure_collector/services/mariadb_servers.py
securicad/azure_collector/services/mysql_servers.py
securicad/azure_collector/services/network_connections.py
securicad/azure_collector/services/network_handling.py
securicad/azure_collector/services/network_interfaces.py
securicad/azure_collector/services/network_security_groups.py
securicad/azure_collector/services/parser_logger.py
securicad/azure_collector/services/postgresql_servers.py
securicad/azure_collector/services/public_ip_addresses.py
securicad/azure_collector/services/route_tables.py
securicad/azure_collector/services/service_buses.py
securicad/azure_collector/services/sql_servers.py
securicad/azure_collector/services/ssh_public_keys.py
securicad/azure_collector/services/storage_accounts.py
securicad/azure_collector/services/virtual_machines.py
securicad/azure_collector/services/vmss.py
securicad/azure_collector/services/vnet_gateways.py
securicad/azure_collector/services/vnets.py
securicad_azure_collector-2.0.4.dist-info/LICENSE
securicad_azure_collector-2.0.4.dist-info/METADATA
securicad_azure_collector-2.0.4.dist-info/NOTICE
securicad_azure_collector-2.0.4.dist-info/WHEEL
securicad_azure_collector-2.0.4.dist-info/entry_points.txt
securicad_azure_collector-2.0.4.dist-info/top_level.txt
securicad_azure_collector-2.0.4.dist-info/RECORD
