Metadata-Version: 2.1
Name: securicad-azure-collector
Version: 2.0.4
Summary: A Python package for collecting Azure data for use in foreseeti's securiCAD products
Home-page: https://github.com/foreseeti/securicad-azure-collector
Author: Foreseeti AB
License: The Apache Software License, Version 2.0
Keywords: securicad,azure,threat,modeling
Platform: UNKNOWN
Classifier: Environment :: Console
Classifier: Intended Audience :: Developers
Classifier: Intended Audience :: Information Technology
Classifier: Intended Audience :: System Administrators
Classifier: License :: OSI Approved
Classifier: License :: OSI Approved :: Apache Software License
Classifier: Natural Language :: English
Classifier: Operating System :: OS Independent
Classifier: Programming Language :: Python
Classifier: Programming Language :: Python :: 3
Classifier: Programming Language :: Python :: 3 :: Only
Classifier: Programming Language :: Python :: 3.8
Classifier: Programming Language :: Python :: 3.9
Classifier: Programming Language :: Python :: 3.10
Classifier: Topic :: Security
Classifier: Topic :: Software Development
Classifier: Topic :: Software Development :: Libraries
Classifier: Topic :: Software Development :: Libraries :: Application Frameworks
Classifier: Topic :: Software Development :: Libraries :: Python Modules
Classifier: Typing :: Typed
Requires-Python: >=3.8
License-File: LICENSE
License-File: NOTICE
Requires-Dist: requests
Requires-Dist: azure-core (==1.19.0)
Requires-Dist: azure-mgmt-resource (==15.0.0)
Requires-Dist: azure-mgmt-subscription (==1.0.0)
Requires-Dist: azure-common (==1.1.26)
Requires-Dist: azure-mgmt-resourcegraph (==7.0.0)
Requires-Dist: azure-mgmt-keyvault (==8.0.0)
Requires-Dist: azure-keyvault-keys (==4.3.1)
Requires-Dist: azure-keyvault-certificates (==4.2.1)
Requires-Dist: azure-keyvault-secrets (==4.2.0)
Requires-Dist: azure-identity (==1.5.0)
Requires-Dist: cffi
Requires-Dist: cryptography
Requires-Dist: azure-storage-blob (==12.6.0)
Requires-Dist: azure-mgmt-storage (==16.0.0)
Requires-Dist: azure-mgmt-authorization (==1.0.0)
Requires-Dist: azure-mgmt-cosmosdb (==6.0.0)
Requires-Dist: msrestazure (==0.6.4)
Requires-Dist: typer
Provides-Extra: dev
Requires-Dist: black ; extra == 'dev'
Requires-Dist: build ; extra == 'dev'
Requires-Dist: isort ; extra == 'dev'
Requires-Dist: mypy ; extra == 'dev'
Requires-Dist: pylint ; extra == 'dev'
Requires-Dist: twine ; extra == 'dev'
